{
  "fqn": "gateway_widgets.gateway_general_chart_statistics",
  "name": "Gateway general chart statistics",
  "deprecated": false,
  "image": "tb-image;/api/images/system/gateway_general_chart_statistics_system_widget_image.png",
  "description": "Provides a real-time chart with statistical data. Displays one of the following: bytes sent to the platform, bytes received from the platform, CPU, RAM, Disk, etc.",
  "descriptor": {
    "type": "timeseries",
    "sizeX": 8,
    "sizeY": 5,
    "resources": [
      {
        "url": "tb-resource;/api/resource/js_module/system/gateway-management-extension.js",
        "isModule": true
      }
    ],
    "templateHtml": "<tb-gateway-statistics [ctx]=ctx [general]='true'></tb-gateway-statistics>",
    "templateCss": ".legend {\n    font-size: 13px;\n    line-height: 10px;\n}\n\n.legend table { \n    border-spacing: 0px;\n    border-collapse: separate;\n}\n\n.mouse-events .flot-overlay {\n    cursor: crosshair; \n}\n\n",
    "controllerScript": "self.onInit = function() {   \n};\n\nself.onDataUpdated = function() {\n};\n\nself.onLatestDataUpdated = function() {\n};\n\nself.onResize = function() {\n};\n\nself.onEditModeChanged = function() {\n};\n\nself.onDestroy = function() {\n};\n\nself.typeParameters = function() {\n    return {\n        hasAdditionalLatestDataKeys: false\n    };\n}\n",
    "settingsSchema": "{}",
    "dataKeySettingsSchema": "{}",
    "latestDataKeySettingsSchema": "{}",
    "settingsDirective": "tb-flot-line-widget-settings",
    "dataKeySettingsDirective": "tb-flot-line-key-settings",
    "latestDataKeySettingsDirective": "tb-flot-latest-key-settings",
    "defaultConfig": "{\"datasources\":[{\"type\":\"function\",\"name\":\"function\",\"dataKeys\":[{\"name\":\"f(x)\",\"type\":\"function\",\"label\":\"First\",\"color\":\"#2196f3\",\"settings\":{\"showLines\":true,\"fillLines\":true,\"showPoints\":false},\"_hash\":0.8587686344902596,\"funcBody\":\"var value = prevValue + Math.random() * 100 - 50;\\nvar multiplier = Math.pow(10, 2 || 0);\\nvar value = Math.round(value * multiplier) / multiplier;\\nif (value < -1000) {\\n\\tvalue = -1000;\\n} else if (value > 1000) {\\n\\tvalue = 1000;\\n}\\nreturn value;\"},{\"name\":\"f(x)\",\"type\":\"function\",\"label\":\"Second\",\"color\":\"#ffc107\",\"settings\":{\"showLines\":true,\"fillLines\":false,\"showPoints\":false},\"_hash\":0.12775350966079668,\"funcBody\":\"var value = prevValue + Math.random() * 100 - 50;\\nvar multiplier = Math.pow(10, 2 || 0);\\nvar value = Math.round(value * multiplier) / multiplier;\\nif (value < -1000) {\\n\\tvalue = -1000;\\n} else if (value > 1000) {\\n\\tvalue = 1000;\\n}\\nreturn value;\"}]}],\"timewindow\":{\"realtime\":{\"timewindowMs\":60000}},\"showTitle\":true,\"backgroundColor\":\"#fff\",\"color\":\"rgba(0, 0, 0, 0.87)\",\"padding\":\"8px\",\"settings\":{\"shadowSize\":4,\"fontColor\":\"#545454\",\"fontSize\":10,\"xaxis\":{\"showLabels\":true,\"color\":\"#545454\"},\"yaxis\":{\"showLabels\":true,\"color\":\"#545454\"},\"grid\":{\"color\":\"#545454\",\"tickColor\":\"#DDDDDD\",\"verticalLines\":true,\"horizontalLines\":true,\"outlineWidth\":1},\"legend\":{\"show\":true,\"position\":\"nw\",\"backgroundColor\":\"#f0f0f0\",\"backgroundOpacity\":0.85,\"labelBoxBorderColor\":\"rgba(1, 1, 1, 0.45)\"},\"decimals\":1,\"stack\":false,\"tooltipIndividual\":false},\"title\":\"Gateway general chart statistics\",\"dropShadow\":true,\"enableFullscreen\":true,\"titleStyle\":{\"fontSize\":\"16px\",\"fontWeight\":400},\"mobileHeight\":null}"
  },
  "tags": [
    "router",
    "bridge",
    "hub",
    "access point",
    "relay",
    "opc ua",
    "opc-ua",
    "modbus",
    "bacnet",
    "odbc",
    "ftp",
    "snmp",
    "mqtt",
    "xmpp",
    "ocpp",
    "ble",
    "bluetooth"
  ]
}
