{
  "providerId": "Apple",
  "additionalInfo": null,
  "accessTokenUri": "https://appleid.apple.com/auth/token",
  "authorizationUri": "https://appleid.apple.com/auth/authorize?response_mode=form_post",
  "scope": ["email","openid","name"],
  "jwkSetUri": "https://appleid.apple.com/auth/keys",
  "userInfoUri": null,
  "clientAuthenticationMethod": "POST",
  "userNameAttributeName": "email",
  "mapperConfig": {
    "type": "APPLE",
    "basic": {
      "emailAttributeKey": "email",
      "firstNameAttributeKey": "firstName",
      "lastNameAttributeKey": "lastName",
      "tenantNameStrategy": "DOMAIN"
    }
  },
  "comment": null,
  "loginButtonIcon": "apple-logo",
  "loginButtonLabel": "Apple",
  "helpLink": "https://developer.apple.com/sign-in-with-apple/get-started/"
}
